{"inkVersion":21,"root":[["\n",{"->":"start"},["done",{"#f":5,"#n":"g-0"}],null],"done",{"start":[["ev","str","^Poppy","/str","str","^Right","/str","str","^Normal","/str",{"x()":"ShowCharacter","exArgs":3},"out","/ev","^ So.. I might have overheard some drunken ramblings I definitely shouldn't have.","\n","ev","str","^Tell me!","/str","/ev",{"*":".^.c-0","flg":20},"ev","str","^You shouldn't spread rumors.","/str","/ev",{"*":".^.c-1","flg":20},{"c-0":["^ ",{"->":"PoppyGossip"},"\n",{"#f":5}],"c-1":["^ ",{"->":"PoppyScold"},"\n",{"#f":5}]}],{"#f":1}],"PoppyGossip":["ev","str","^Poppy","/str",{"x()":"HideCharacter","exArgs":1},"out","/ev","^ ","ev","str","^Player","/str","str","^Right","/str","str","^Normal","/str",{"x()":"ShowCharacter","exArgs":3},"out","/ev","^ Oh? Spill! I NEED to know.","\n","ev","str","^Player","/str",{"x()":"HideCharacter","exArgs":1},"out","/ev","^ ","ev","str","^Poppy","/str","str","^Right","/str","str","^Normal","/str",{"x()":"ShowCharacter","exArgs":3},"out","/ev","^ I could tell you, but that would make me a bad bartender, wouldn't it?","\n","ev","str","^Poppy","/str",{"x()":"HideCharacter","exArgs":1},"out","/ev","^ ","ev","str","^Player","/str","str","^Right","/str","str","^Normal","/str",{"x()":"ShowCharacter","exArgs":3},"out","/ev","^ Oh, come on. Just a little?","\n","ev","str","^Player","/str",{"x()":"HideCharacter","exArgs":1},"out","/ev","^ ","ev","str","^Poppy","/str","str","^Right","/str","str","^Happy","/str",{"x()":"ShowCharacter","exArgs":3},"out","/ev","^ Fine, fine. Let's just say, someone in town has a very strong crush. And no, I won't say who. That's for you to figure out.","\n","ev","str","^Poppy","/str",{"x()":"HideCharacter","exArgs":1},"out","/ev","^ ","ev","str","^Player","/str","str","^Right","/str","str","^Normal","/str",{"x()":"ShowCharacter","exArgs":3},"out","/ev","^ You tease!","\n","ev","str","^Player","/str",{"x()":"HideCharacter","exArgs":1},"out","/ev","^ ","ev","str","^Poppy","/str","str","^Right","/str","str","^Happy","/str",{"x()":"ShowCharacter","exArgs":3},"out","/ev","^ I have to keep things interesting somehow.","\n","ev",{"VAR?":"PoppyTrust"},10,"+",{"VAR=":"PoppyTrust","re":true},"/ev","end",{"#f":1}],"PoppyScold":["ev","str","^Poppy","/str",{"x()":"HideCharacter","exArgs":1},"out","/ev","^ ","ev","str","^Player","/str","str","^Right","/str","str","^Normal","/str",{"x()":"ShowCharacter","exArgs":3},"out","/ev","^ You know, eavesdropping and spreading rumors isn't great.","\n","ev","str","^Player","/str",{"x()":"HideCharacter","exArgs":1},"out","/ev","^ ","ev","str","^Poppy","/str","str","^Right","/str","str","^Suspicious","/str",{"x()":"ShowCharacter","exArgs":3},"out","/ev","^ Oh, I wasn't eavesdropping, mate. People just forget I exist when they've had a few drinks.","\n","ev","str","^Poppy","/str",{"x()":"HideCharacter","exArgs":1},"out","/ev","^ ","ev","str","^Player","/str","str","^Right","/str","str","^Normal","/str",{"x()":"ShowCharacter","exArgs":3},"out","/ev","^ That still doesn't mean you should spread whatever you heard around.","\n","ev","str","^Player","/str",{"x()":"HideCharacter","exArgs":1},"out","/ev","^ ","ev","str","^Poppy","/str","str","^Right","/str","str","^Normal","/str",{"x()":"ShowCharacter","exArgs":3},"out","/ev","^ Just say you don't want to know, that's fine. Someone has to make this town a little more interesting, so it might as well be me.","\n","ev",{"VAR?":"PoppyTrust"},10,"-",{"VAR=":"PoppyTrust","re":true},"/ev","end",{"#f":1}],"global decl":["ev",0,{"VAR=":"Trust"},0,{"VAR=":"Suspicion"},0,{"VAR=":"GeraldTrust"},0,{"VAR=":"SebastianTrust"},0,{"VAR=":"CharlieTrust"},0,{"VAR=":"MeganTrust"},0,{"VAR=":"AvaTrust"},0,{"VAR=":"BruceTrust"},0,{"VAR=":"MaddieTrust"},0,{"VAR=":"PoppyTrust"},0,{"VAR=":"LindaTrust"},0,{"VAR=":"JeremyTrust"},"str","^Y/N","/str",{"VAR=":"PlayerName"},"/ev","end",null],"#f":1}],"listDefs":{}}